hydra_ssh/.mypy_cache/.gitignore
hydra_ssh/.mypy_cache/3.13/@plugins_snapshot.json
hydra_ssh/.mypy_cache/3.13/__future__.data.json
hydra_ssh/.mypy_cache/3.13/__future__.meta.json
hydra_ssh/.mypy_cache/3.13/_ast.data.json
hydra_ssh/.mypy_cache/3.13/_ast.meta.json
hydra_ssh/.mypy_cache/3.13/_asyncio.data.json
hydra_ssh/.mypy_cache/3.13/_asyncio.meta.json
hydra_ssh/.mypy_cache/3.13/_blake2.data.json
hydra_ssh/.mypy_cache/3.13/_blake2.meta.json
hydra_ssh/.mypy_cache/3.13/_codecs.data.json
hydra_ssh/.mypy_cache/3.13/_codecs.meta.json
hydra_ssh/.mypy_cache/3.13/_collections_abc.data.json
hydra_ssh/.mypy_cache/3.13/_collections_abc.meta.json
hydra_ssh/.mypy_cache/3.13/_contextvars.data.json
hydra_ssh/.mypy_cache/3.13/_contextvars.meta.json
hydra_ssh/.mypy_cache/3.13/_ctypes.data.json
hydra_ssh/.mypy_cache/3.13/_ctypes.meta.json
hydra_ssh/.mypy_cache/3.13/_decimal.data.json
hydra_ssh/.mypy_cache/3.13/_decimal.meta.json
hydra_ssh/.mypy_cache/3.13/_frozen_importlib.data.json
hydra_ssh/.mypy_cache/3.13/_frozen_importlib.meta.json
hydra_ssh/.mypy_cache/3.13/_frozen_importlib_external.data.json
hydra_ssh/.mypy_cache/3.13/_frozen_importlib_external.meta.json
hydra_ssh/.mypy_cache/3.13/_hashlib.data.json
hydra_ssh/.mypy_cache/3.13/_hashlib.meta.json
hydra_ssh/.mypy_cache/3.13/_io.data.json
hydra_ssh/.mypy_cache/3.13/_io.meta.json
hydra_ssh/.mypy_cache/3.13/_pickle.data.json
hydra_ssh/.mypy_cache/3.13/_pickle.meta.json
hydra_ssh/.mypy_cache/3.13/_queue.data.json
hydra_ssh/.mypy_cache/3.13/_queue.meta.json
hydra_ssh/.mypy_cache/3.13/_random.data.json
hydra_ssh/.mypy_cache/3.13/_random.meta.json
hydra_ssh/.mypy_cache/3.13/_sitebuiltins.data.json
hydra_ssh/.mypy_cache/3.13/_sitebuiltins.meta.json
hydra_ssh/.mypy_cache/3.13/_socket.data.json
hydra_ssh/.mypy_cache/3.13/_socket.meta.json
hydra_ssh/.mypy_cache/3.13/_ssl.data.json
hydra_ssh/.mypy_cache/3.13/_ssl.meta.json
hydra_ssh/.mypy_cache/3.13/_stat.data.json
hydra_ssh/.mypy_cache/3.13/_stat.meta.json
hydra_ssh-1.0.2.dist-info/METADATA
hydra_ssh-1.0.2.dist-info/WHEEL
hydra_ssh-1.0.2.dist-info/entry_points.txt
hydra_ssh-1.0.2.dist-info/RECORD
