Metadata-Version: 2.3
Name: hydra-ssh
Version: 1.0.2
Summary: A command-line tool to execute commands on multiple remote hosts
License: MIT
Author: Chaiwat Suttipongsakul
Author-email: cwt@bashell.com
Requires-Python: >=3.10
Classifier: License :: OSI Approved :: MIT License
Classifier: Programming Language :: Python :: 3
Classifier: Programming Language :: Python :: 3.10
Classifier: Programming Language :: Python :: 3.11
Classifier: Programming Language :: Python :: 3.12
Classifier: Programming Language :: Python :: 3.13
Requires-Dist: asyncssh (>=2.20.0,<3.0.0)
Requires-Dist: uvloop (>=0.21.0,<0.22.0) ; sys_platform != "win32"
Requires-Dist: winloop (>=0.1.8,<0.2.0) ; sys_platform == "win32"
Project-URL: Homepage, https://sr.ht/~cwt/hydra
Project-URL: Repository, https://hg.sr.ht/~cwt/hydra
